sciplot/__init__.py
sciplot/__main__.py
sciplot/sciplotUI.py
sciplot/sciplotUI_addon.py
sciplot/data/__init__.py
sciplot/data/bars.py
sciplot/data/generic.py
sciplot/data/images.py
sciplot/data/lines.py
sciplot/data/polycollections.py
sciplot/data/special.py
sciplot/tests/__init__.py
sciplot/tests/test_generic.py
sciplot/tests/test_utils.py
sciplot/ui/__init__.py
sciplot/ui/dialogs.py
sciplot/ui/qt_Plotter.py
sciplot/ui/widget_mpl.py
sciplot/ui/models/__init__.py
sciplot/ui/models/abstract.py
sciplot/ui/models/bars.py
sciplot/ui/models/fillbetween.py
sciplot/ui/models/images.py
sciplot/ui/models/lines.py
sciplot/ui/qt5-creator/__init__.py
sciplot/ui/qt5-creator/ui_Plotter.ui
sciplot/utils/__init__.py
sciplot/utils/general.py
sciplot/utils/mplstyle.py
sciplot_pyqt-0.2.3.dist-info/LICENSE.md
sciplot_pyqt-0.2.3.dist-info/METADATA
sciplot_pyqt-0.2.3.dist-info/WHEEL
sciplot_pyqt-0.2.3.dist-info/top_level.txt
sciplot_pyqt-0.2.3.dist-info/RECORD
