Metadata-Version: 2.1
Name: sciplot-pyqt
Version: 0.2.3
Summary: A small matplotlib wrapper/UI for creating                      publication-ready plots, graphs, and images
Home-page: http://github.com/CCampJr/SciPlot-PyQt
Author: Charles H. Camp Jr.
Author-email: charles.camp@nist.gov
License: Public Domain
Platform: UNKNOWN
Classifier: Development Status :: 3 - Alpha
Classifier: Intended Audience :: Developers
Classifier: Intended Audience :: Science/Research
Classifier: Operating System :: OS Independent
Classifier: Environment :: X11 Applications :: Qt
Classifier: Programming Language :: Python :: 3 :: Only
Classifier: Programming Language :: Python :: 3.4
Classifier: Programming Language :: Python :: 3.5
Classifier: Programming Language :: Python :: 3.6
Classifier: Topic :: Scientific/Engineering :: Visualization
License-File: LICENSE.md
Requires-Dist: numpy
Requires-Dist: matplotlib
